huaweicloudsdkoptverse/__init__.py
huaweicloudsdkoptverse/v2/__init__.py
huaweicloudsdkoptverse/v2/optverse_async_client.py
huaweicloudsdkoptverse/v2/optverse_client.py
huaweicloudsdkoptverse/v2/model/__init__.py
huaweicloudsdkoptverse/v2/model/create_task_request.py
huaweicloudsdkoptverse/v2/model/create_task_response.py
huaweicloudsdkoptverse/v2/model/delete_task_request.py
huaweicloudsdkoptverse/v2/model/delete_task_response.py
huaweicloudsdkoptverse/v2/model/list_task_request.py
huaweicloudsdkoptverse/v2/model/list_task_response.py
huaweicloudsdkoptverse/v2/model/show_task_request.py
huaweicloudsdkoptverse/v2/model/show_task_response.py
huaweicloudsdkoptverse/v2/model/task_dto.py
huaweicloudsdkoptverse/v2/model/task_list_item_vo.py
huaweicloudsdkoptverse/v2/region/__init__.py
huaweicloudsdkoptverse/v2/region/optverse_region.py
huaweicloudsdkoptverse-3.1.184.dist-info/METADATA
huaweicloudsdkoptverse-3.1.184.dist-info/WHEEL
huaweicloudsdkoptverse-3.1.184.dist-info/licenses/LICENSE
huaweicloudsdkoptverse-3.1.184.dist-info/RECORD
